exitter/__init__.py
exitter-1.1.2.dist-info/METADATA
exitter-1.1.2.dist-info/WHEEL
exitter-1.1.2.dist-info/license.txt
exitter-1.1.2.dist-info/top_level.txt
exitter-1.1.2.dist-info/RECORD
