Metadata-Version: 2.1
Name: exitter
Version: 1.1.2
Summary: A package which helps you code the exit loop in python
Home-page: https://github.com/Pranay-Chopra/exitter
Author: Pranay Chopra
Author-email: pranaychopra2007@gmail.com
License: UNKNOWN
Platform: UNKNOWN
Classifier: Programming Language :: Python :: 3
Classifier: License :: OSI Approved :: MIT License
Classifier: Operating System :: OS Independent
Requires-Python: >=1.1
